[
    {
        "id":"1",
        "title": "Almond bar",
        "price": 150,
        "img": "./img/almondBar.jpg",
        "URLImg": "https://i.postimg.cc/c1P7PhDq/elden.jpg"
    },
    {
        "id":"2",
        "title": "Chocolate bar",
        "price": 120,
        "img": "./img/chocolateBar.jpg",
        "URLImg": "https://i.postimg.cc/RCWQPyLQ/dying.jpg"
    },
    {
        "id":"3",
        "title": "Banana bar",
        "price": 120,
        "img": "./img/chocolateBar.jpg",
        "URLImg": "https://i.postimg.cc/RCWQPyLQ/dying.jpg"
    }
]
